llmtricks/__init__.py
llmtricks/_version.py
llmtricks/clients.py
llmtricks/reason.py
llmtricks-0.0.5.dist-info/METADATA
llmtricks-0.0.5.dist-info/WHEEL
llmtricks-0.0.5.dist-info/top_level.txt
llmtricks-0.0.5.dist-info/RECORD
